{"name":"Mohammedaljunidy","tagline":"Mohammedaljunidy","body":"### مرحبا بكم في جيثب الصفحات. هذه المولدات صفحة التلقائي هو أسهل طريقة لإنشاء صفحات جميلة لجميع المشاريع الخاصة بك. الكاتب المحتوى الخاص بك الصفحة هنا [باستخدام جيثب بنكهة تخفيض السعر] (https://guides.github.com/features/mastering-markdown/)، حدد قالب وضعت من قبل المصمم، ونشرها. بعد إنشاء الصفحة الخاصة بك، يمكنك إجراء فحص `فرع جديد GH-pages` محليا. إذا كنت تستخدم جيثب سطح المكتب، ببساطة مزامنة المخزون الخاص بك وسترى الفرع الجديد. ### مصمم قوالب لقد وضعت بعض القوالب وسيم لتتمكن من استخدامها. المضي قدما وانقر فوق \"متابعة لتخطيطات 'لتصفح خلالهم. يمكنك الذهاب بسهولة إلى تعديل صفحتك قبل النشر. بعد نشر الصفحة الخاصة بك، يمكنك إعادة النظر في مولد صفحة والتحول إلى موضوع آخر. سيتم الحفاظ محتوى الصفحة الخاصة بك. ### إنشاء صفحات يدويا إذا كنت تفضل عدم استخدام مولد التلقائي، ودفع فرع يدعى `غ pages` إلى المخزون الخاص بك لإنشاء صفحة يدويا. بالإضافة إلى دعم المحتوى HTML العادية، الصفحات جيثب دعم جيكل، بسيط، بلوق تدرك ثابت موقع المولد. جيكل يجعل من السهل إنشاء رؤوس مستوى الموقع والتذييلات دون الحاجة إلى نسخها عبر كل صفحة. كما يقدم الدعم بلوق ذكي وغيرها من الميزات المتقدمة النموذجيه. ### المؤلفين والمساهمين يمكنكmention اسم المستخدم جيثب لتوليد تصل إلى ملفهم الشخصي. سوف ينتج `` <A> عنصر يرتبط جيثب الملف المساهم. على سبيل المثال: في عام 2007، كريس Wanstrath (defunkt)، PJ Hyett (pjhyett)، وتوم بريستون فيرنر (mojombo) التي تأسست جيثب. ### دعم أو الاتصال تواجه مشكلة مع الصفحات؟ تحقق من [وثائق] (https://help.github.com/pages) أو [الاتصال بالدعم] (https://github.com/contact)، ونحن سوف تساعدك على ترتيب هذا الامر.\r\n","google":"Mohammedaljunidy","note":"Don't delete this file! It's used internally to help with page regeneration."}